{
  "frame": 73,
  "skeleton_type": "anatomical_fk_21",
  "skeleton_height_cm": 163.8,
  "height_locked": true,
  "facing_direction": "front_left_slight",
  "body_yaw_deg": 345.0,
  "avg_fitting_error_cm": 24.60,
  "contour_containment_pass": true,
  "contour_violations": 0,
  "grid_resolution_cm": 2.0,
  "grid_origin": [-100.0, 240.0, -170.0],
  "iccs_origin_world": [24.69, 460.47, -79.53],
  "cluster_voxel_count": 2206,
  "joints_in_cluster": 0,
  "pose_angles": {
  "lower_spine": {"rx": 1.12, "ry": -4.26, "rz": -0.04}, 
  "upper_spine": {"rx": 2.31, "ry": 1.98, "rz": -0.07}, 
  "neck": {"rx": -10.13, "ry": 0.3, "rz": 0.17}, 
  "head": {"rx": 0.0, "ry": 0.0, "rz": 0.0}, 
  "shoulder_offset_l": {"rx": -3.37, "ry": 3.15, "rz": 0.0}, 
  "shoulder_offset_r": {"rx": -3.37, "ry": 3.15, "rz": 0.0}, 
  "upper_arm_l": {"rx": -8.18, "ry": -20.83, "rz": 13.65}, 
  "forearm_l": {"rx": 0.0, "ry": 0.0, "rz": 12.25}, 
  "upper_arm_r": {"rx": -11.5, "ry": 36.39, "rz": -17.19}, 
  "forearm_r": {"rx": 2.79, "ry": 0.0, "rz": 30.74}, 
  "thigh_l": {"rx": -8.12, "ry": 24.74, "rz": -1.98}, 
  "shin_l": {"rx": 0.0, "ry": 0.0, "rz": 0.0}, 
  "thigh_r": {"rx": -9.67, "ry": 33.67, "rz": -3.12}, 
  "shin_r": {"rx": 0.0, "ry": 0.0, "rz": 0.0}},
  "movement_index": {"frame": 73, "movement_label": "UNKNOWN", "index_code": "O-|S1|O+|FA|EA|S0|O-|S0|S0|S0|S0|S0|EA|F+|EA|F+|F+|FA|EA|EA|F-|EA|CL|FA|F+|FA|FA|FA|F+|F+|S1|F+|CL|CL|F+|F+|S0|F-", "symmetry_score": 0.4, "global": {"origin": [24.7, 460.5, -79.5], "origin_velocity": [4.3, 5.2, -0.1], "translation_speed": 6.8, "vertical_velocity": -0.1, "yaw": 165.0, "yaw_rate": -7.3}, "channels": {"lower_spine.rx": {"theta": 1.1, "theta_dot": -4.3, "theta_ddot": -4.2, "theta_norm": -0.2, "theta_dot_norm": -0.1, "code": "O-", "periodic": true, "frequency": 4.0, "phase": 5.2, "at_limit": false}, "lower_spine.ry": {"theta": -4.3, "theta_dot": 0.1, "theta_ddot": 1.1, "theta_norm": -0.1, "theta_dot_norm": 0.0, "code": "S1", "periodic": false, "frequency": 0, "phase": null, "at_limit": false}, "lower_spine.rz": {"theta": -0.0, "theta_dot": 0.2, "theta_ddot": 0.2, "theta_norm": -0.0, "theta_dot_norm": 0.0, "code": "O+", "periodic": true, "frequency": 4.0, "phase": 0.0, "at_limit": false}, "upper_spine.rx": {"theta": 2.3, "theta_dot": 5.8, "theta_ddot": 5.7, "theta_norm": -0.1, "theta_dot_norm": 0.2, "code": "FA", "periodic": false, "frequency": 0, "phase": null, "at_limit": false}, "upper_spine.ry": {"theta": 2.0, "theta_dot": -0.8, "theta_ddot": -1.6, "theta_norm": 0.1, "theta_dot_norm": -0.0, "code": "EA", "periodic": false, "frequency": 0, "phase": null, "at_limit": false}, "upper_spine.rz": {"theta": -0.1, "theta_dot": 0.0, "theta_ddot": 0.0, "theta_norm": -0.0, "theta_dot_norm": 0.0, "code": "S0", "periodic": false, "frequency": 0, "phase": null, "at_limit": false}, "neck.rx": {"theta": -10.1, "theta_dot": -2.0, "theta_ddot": -1.9, "theta_norm": -0.4, "theta_dot_norm": -0.0, "code": "O-", "periodic": true, "frequency": 4.0, "phase": 5.2, "at_limit": false}, "neck.ry": {"theta": 0.3, "theta_dot": 0.8, "theta_ddot": 1.2, "theta_norm": 0.0, "theta_dot_norm": 0.0, "code": "S0", "periodic": false, "frequency": 0, "phase": null, "at_limit": false}, "neck.rz": {"theta": 0.2, "theta_dot": 0.0, "theta_ddot": -0.1, "theta_norm": 0.0, "theta_dot_norm": 0.0, "code": "S0", "periodic": false, "frequency": 0, "phase": null, "at_limit": false}, "head.rx": {"theta": 0.0, "theta_dot": 0.0, "theta_ddot": 0.0, "theta_norm": 0.0, "theta_dot_norm": 0.0, "code": "S0", "periodic": false, "frequency": 0, "phase": null, "at_limit": false}, "head.ry": {"theta": 0.0, "theta_dot": 0.0, "theta_ddot": 0.0, "theta_norm": 0.0, "theta_dot_norm": 0.0, "code": "S0", "periodic": false, "frequency": 0, "phase": null, "at_limit": false}, "head.rz": {"theta": 0.0, "theta_dot": 0.0, "theta_ddot": 0.0, "theta_norm": 0.0, "theta_dot_norm": 0.0, "code": "S0", "periodic": false, "frequency": 0, "phase": null, "at_limit": false}, "shoulder_offset_l.rx": {"theta": -3.4, "theta_dot": -1.5, "theta_ddot": -1.5, "theta_norm": -0.5, "theta_dot_norm": -0.1, "code": "EA", "periodic": false, "frequency": 0, "phase": null, "at_limit": false}, "shoulder_offset_l.ry": {"theta": 3.2, "theta_dot": 1.3, "theta_ddot": 0.7, "theta_norm": 0.2, "theta_dot_norm": 0.1, "code": "F+", "periodic": false, "frequency": 0, "phase": null, "at_limit": false}, "shoulder_offset_r.rx": {"theta": -3.4, "theta_dot": -1.5, "theta_ddot": -1.5, "theta_norm": -0.5, "theta_dot_norm": -0.1, "code": "EA", "periodic": false, "frequency": 0, "phase": null, "at_limit": false}, "shoulder_offset_r.ry": {"theta": 3.2, "theta_dot": 1.3, "theta_ddot": 0.7, "theta_norm": 0.2, "theta_dot_norm": 0.1, "code": "F+", "periodic": false, "frequency": 0, "phase": null, "at_limit": false}, "upper_arm_l.rx": {"theta": -8.2, "theta_dot": 7.4, "theta_ddot": 4.7, "theta_norm": -0.6, "theta_dot_norm": 0.1, "code": "F+", "periodic": false, "frequency": 0, "phase": null, "at_limit": false}, "upper_arm_l.ry": {"theta": -20.8, "theta_dot": 9.4, "theta_ddot": 9.2, "theta_norm": -0.8, "theta_dot_norm": 0.1, "code": "FA", "periodic": false, "frequency": 0, "phase": null, "at_limit": false}, "upper_arm_l.rz": {"theta": 13.6, "theta_dot": -10.3, "theta_ddot": -6.7, "theta_norm": 0.2, "theta_dot_norm": -0.1, "code": "EA", "periodic": false, "frequency": 0, "phase": null, "at_limit": false}, "upper_arm_r.rx": {"theta": -11.5, "theta_dot": -9.7, "theta_ddot": -11.5, "theta_norm": -0.6, "theta_dot_norm": -0.1, "code": "EA", "periodic": false, "frequency": 0, "phase": null, "at_limit": false}, "upper_arm_r.ry": {"theta": 36.4, "theta_dot": -3.1, "theta_ddot": -0.6, "theta_norm": 0.9, "theta_dot_norm": -0.0, "code": "F-", "periodic": false, "frequency": 0, "phase": null, "at_limit": false}, "upper_arm_r.rz": {"theta": -17.2, "theta_dot": -14.6, "theta_ddot": -16.8, "theta_norm": -0.2, "theta_dot_norm": -0.2, "code": "EA", "periodic": false, "frequency": 0, "phase": null, "at_limit": false}, "forearm_l.rx": {"theta": 0.0, "theta_dot": 0.0, "theta_ddot": 0.0, "theta_norm": -1.0, "theta_dot_norm": 0.0, "code": "CL", "periodic": false, "frequency": 0, "phase": null, "at_limit": true}, "forearm_l.rz": {"theta": 12.2, "theta_dot": 9.1, "theta_ddot": 5.4, "theta_norm": 0.1, "theta_dot_norm": 0.1, "code": "FA", "periodic": false, "frequency": 0, "phase": null, "at_limit": false}, "forearm_r.rx": {"theta": 2.8, "theta_dot": 2.8, "theta_ddot": 1.4, "theta_norm": -1.0, "theta_dot_norm": 0.0, "code": "F+", "periodic": false, "frequency": 0, "phase": null, "at_limit": true}, "forearm_r.rz": {"theta": 30.7, "theta_dot": 32.8, "theta_ddot": 15.9, "theta_norm": 0.3, "theta_dot_norm": 0.4, "code": "FA", "periodic": false, "frequency": 0, "phase": null, "at_limit": false}, "thigh_l.rx": {"theta": -8.1, "theta_dot": 6.5, "theta_ddot": 3.1, "theta_norm": -0.7, "theta_dot_norm": 0.1, "code": "FA", "periodic": false, "frequency": 0, "phase": null, "at_limit": false}, "thigh_l.ry": {"theta": 24.7, "theta_dot": 6.5, "theta_ddot": 9.0, "theta_norm": 0.6, "theta_dot_norm": 0.1, "code": "FA", "periodic": false, "frequency": 0, "phase": null, "at_limit": false}, "thigh_l.rz": {"theta": -2.0, "theta_dot": 1.5, "theta_ddot": 0.5, "theta_norm": -0.0, "theta_dot_norm": 0.0, "code": "F+", "periodic": false, "frequency": 0, "phase": null, "at_limit": false}, "thigh_r.rx": {"theta": -9.7, "theta_dot": 2.6, "theta_ddot": 0.0, "theta_norm": -0.7, "theta_dot_norm": 0.0, "code": "F+", "periodic": false, "frequency": 0, "phase": null, "at_limit": false}, "thigh_r.ry": {"theta": 33.7, "theta_dot": -0.5, "theta_ddot": 1.3, "theta_norm": 0.7, "theta_dot_norm": -0.0, "code": "S1", "periodic": false, "frequency": 0, "phase": null, "at_limit": false}, "thigh_r.rz": {"theta": -3.1, "theta_dot": 1.8, "theta_ddot": 0.9, "theta_norm": -0.1, "theta_dot_norm": 0.0, "code": "F+", "periodic": false, "frequency": 0, "phase": null, "at_limit": false}, "shin_l.rx": {"theta": 0.0, "theta_dot": 0.0, "theta_ddot": 0.0, "theta_norm": -1.0, "theta_dot_norm": 0.0, "code": "CL", "periodic": false, "frequency": 0, "phase": null, "at_limit": true}, "shin_r.rx": {"theta": 0.0, "theta_dot": 0.0, "theta_ddot": 0.0, "theta_norm": -1.0, "theta_dot_norm": 0.0, "code": "CL", "periodic": false, "frequency": 0, "phase": null, "at_limit": true}}, "kuramoto": {"r_global": 0.0, "r_legs": 0.1, "r_arms": 0.0, "r_spine": 0.5, "r_head_stability": 0.5, "r_legs_arms": 0.0, "r_spine_head": 0.0, "master_phase": 3.3, "master_frequency": 0.0, "desync_score": 0.7, "law_violations": 0, "laws": {"counter_swing": true, "bilateral_antiphase": true, "torso_counter_rotation": true, "head_stability": true, "amplitude_proportion": true}, "coupling_errors": {"r_hip\u2192r_knee": 1.9, "r_knee\u2192r_ankle": 2.2, "l_hip\u2192l_knee": 2.4, "l_knee\u2192l_ankle": 1.7, "r_shoulder\u2192r_elbow": 1.1, "r_elbow\u2192r_wrist": 0.2, "l_shoulder\u2192l_elbow": 1.2, "l_elbow\u2192l_wrist": 0.2, "r_hip\u2194l_hip": 3.1, "l_hip\u2194r_hip": 3.1, "r_knee\u2194l_knee": 2.6, "l_knee\u2194r_knee": 2.6, "r_shoulder\u2194l_shoulder": 3.0, "l_shoulder\u2194r_shoulder": 3.0, "r_hip\u2192l_shoulder (counterswing)": 3.1, "l_shoulder\u2192r_hip": 3.1, "l_hip\u2192r_shoulder (counterswing)": 3.1, "r_shoulder\u2192l_hip": 3.1, "pelvis\u2194shoulders (counter-rotate)": 2.1, "shoulders\u2194pelvis": 2.1, "pelvis\u2192spine_mid": 2.6}}},
  "spine_curve": [[24.7, 460.5, -79.5], [26.3, 460.3, -55.8], [27.2, 460.4, -32.1], [27.4, 459.9, -19.0]],
  "joints": [
    {"joint_idx": 0, "joint_name": "nose", "valid": true, "world_coords": [22.4, 440.9, -16.3], "y_plane_cell_index": [61, 100, 76], "cell_source": "estimated", "cell_metadata": {}, "iccs_coords": [-2.9, 19.5, 63.2], "fitting_error_cm": 15.4},
    {"joint_idx": 1, "joint_name": "left_eye", "valid": true, "world_coords": [30.2, 457.0, -14.2], "y_plane_cell_index": [65, 108, 77], "cell_source": "estimated", "cell_metadata": {}, "iccs_coords": [-6.2, 1.9, 65.3], "fitting_error_cm": 13.4},
    {"joint_idx": 2, "joint_name": "right_eye", "valid": true, "world_coords": [23.9, 458.7, -14.1], "y_plane_cell_index": [61, 109, 77], "cell_source": "estimated", "cell_metadata": {}, "iccs_coords": [0.3, 1.9, 65.5], "fitting_error_cm": 12.2},
    {"joint_idx": 3, "joint_name": "left_ear", "valid": true, "world_coords": [33.8, 458.2, -17.6], "y_plane_cell_index": [66, 109, 76], "cell_source": "estimated", "cell_metadata": {}, "iccs_coords": [-9.4, -0.2, 62.0], "fitting_error_cm": 13.4},
    {"joint_idx": 4, "joint_name": "right_ear", "valid": true, "world_coords": [21.1, 461.6, -17.2], "y_plane_cell_index": [60, 110, 76], "cell_source": "estimated", "cell_metadata": {}, "iccs_coords": [3.7, -0.1, 62.4], "fitting_error_cm": 7.0},
    {"joint_idx": 5, "joint_name": "left_shoulder", "valid": true, "world_coords": [44.6, 455.8, -32.0], "y_plane_cell_index": [72, 107, 69], "cell_source": "estimated", "cell_metadata": {}, "iccs_coords": [-20.4, -0.7, 47.6], "fitting_error_cm": 6.0},
    {"joint_idx": 6, "joint_name": "right_shoulder", "valid": true, "world_coords": [9.8, 464.9, -32.2], "y_plane_cell_index": [54, 112, 68], "cell_source": "estimated", "cell_metadata": {}, "iccs_coords": [15.6, -0.5, 47.3], "fitting_error_cm": 1.5},
    {"joint_idx": 7, "joint_name": "left_elbow", "valid": true, "world_coords": [59.3, 462.8, -56.6], "y_plane_cell_index": [79, 111, 56], "cell_source": "estimated", "cell_metadata": {"centroid": [58.9, 462.5, -56.3], "density": 3, "normal": [0, 1, 0], "has_neighbors_above": false, "has_neighbors_below": true, "pattern": 17}, "iccs_coords": [-32.8, -11.2, 23.0], "fitting_error_cm": 99.9},
    {"joint_idx": 8, "joint_name": "right_elbow", "valid": true, "world_coords": [-2.0, 469.6, -58.9], "y_plane_cell_index": [48, 114, 55], "cell_source": "estimated", "cell_metadata": {}, "iccs_coords": [28.1, -1.9, 20.6], "fitting_error_cm": 81.1},
    {"joint_idx": 9, "joint_name": "left_wrist", "valid": true, "world_coords": [70.7, 468.3, -75.7], "y_plane_cell_index": [85, 114, 47], "cell_source": "estimated", "cell_metadata": {}, "iccs_coords": [-42.4, -19.4, 3.8], "fitting_error_cm": 78.8},
    {"joint_idx": 10, "joint_name": "right_wrist", "valid": true, "world_coords": [-11.5, 471.7, -79.6], "y_plane_cell_index": [44, 115, 45], "cell_source": "estimated", "cell_metadata": {}, "iccs_coords": [37.9, -1.5, -0.1], "fitting_error_cm": 59.2},
    {"joint_idx": 11, "joint_name": "left_hip", "valid": true, "world_coords": [38.1, 456.9, -79.7], "y_plane_cell_index": [69, 108, 45], "cell_source": "estimated", "cell_metadata": {}, "iccs_coords": [-13.9, -0.0, -0.1], "fitting_error_cm": 7.9},
    {"joint_idx": 12, "joint_name": "right_hip", "valid": true, "world_coords": [11.2, 464.0, -79.4], "y_plane_cell_index": [55, 112, 45], "cell_source": "estimated", "cell_metadata": {}, "iccs_coords": [13.9, 0.0, 0.1], "fitting_error_cm": 7.9},
    {"joint_idx": 13, "joint_name": "left_knee", "valid": true, "world_coords": [56.9, 471.6, -111.9], "y_plane_cell_index": [78, 115, 29], "cell_source": "estimated", "cell_metadata": {"has_neighbors_above": false, "has_neighbors_below": true, "pattern": 17}, "iccs_coords": [-28.3, -19.1, -32.4], "fitting_error_cm": 3.2},
    {"joint_idx": 14, "joint_name": "right_knee", "valid": true, "world_coords": [36.0, 459.2, -110.6], "y_plane_cell_index": [68, 109, 29], "cell_source": "estimated", "cell_metadata": {"centroid": [36.7, 458.5, -111.1], "density": 7, "normal": [-0.0, 1.0, -0.0], "has_neighbors_above": false, "has_neighbors_below": true, "pattern": 18, "surface_type": "OBSERVED"}, "iccs_coords": [-11.3, -1.7, -31.0], "fitting_error_cm": 11.1},
    {"joint_idx": 15, "joint_name": "left_ankle", "valid": true, "world_coords": [75.7, 486.3, -144.2], "y_plane_cell_index": [87, 123, 12], "cell_source": "estimated", "cell_metadata": {}, "iccs_coords": [-42.6, -38.1, -64.7], "fitting_error_cm": 0.0},
    {"joint_idx": 16, "joint_name": "right_ankle", "valid": true, "world_coords": [60.9, 454.3, -141.7], "y_plane_cell_index": [80, 107, 14], "cell_source": "estimated", "cell_metadata": {}, "iccs_coords": [-36.5, -3.5, -62.2], "fitting_error_cm": 0.0},
    {"joint_idx": 17, "joint_name": "head_center", "valid": true, "world_coords": [27.4, 459.9, -19.0], "y_plane_cell_index": [63, 109, 75], "cell_source": "computed", "cell_metadata": {}, "iccs_coords": [-2.8, -0.2, 60.5], "derived_from": "midpoint(left_ear[3], right_ear[4])"},
    {"joint_idx": 18, "joint_name": "shoulder_center", "valid": true, "world_coords": [27.2, 460.4, -32.1], "y_plane_cell_index": [63, 110, 68], "cell_source": "computed", "cell_metadata": {}, "iccs_coords": [-2.4, -0.6, 47.4], "derived_from": "midpoint(left_shoulder[5], right_shoulder[6])"},
    {"joint_idx": 19, "joint_name": "pelvis_center", "valid": true, "world_coords": [24.7, 460.5, -79.5], "y_plane_cell_index": [62, 110, 45], "cell_source": "computed", "cell_metadata": {}, "derived_from": "iccs_origin / midpoint(left_hip[11], right_hip[12])"},
    {"joint_idx": 20, "joint_name": "spine_mid", "valid": true, "world_coords": [26.3, 460.3, -55.8], "y_plane_cell_index": [63, 110, 57], "cell_source": "computed", "cell_metadata": {}, "iccs_coords": [-1.6, -0.3, 23.7], "derived_from": "midpoint(shoulder_center[18], pelvis_center[19])"}
  ],
  "pose_estimator_joints": [
    [22.42, 440.85, -16.28],
    [30.20, 457.02, -14.25],
    [23.87, 458.71, -14.06],
    [33.81, 458.19, -17.56],
    [21.15, 461.57, -17.18],
    [44.61, 455.82, -31.96],
    [9.75, 464.95, -32.25],
    [59.27, 462.83, -56.56],
    [-2.01, 469.55, -58.89],
    [70.68, 468.27, -75.69],
    [-11.54, 471.73, -79.64],
    [38.14, 456.89, -79.67],
    [11.23, 464.04, -79.39],
    [56.94, 471.58, -111.94],
    [36.04, 459.19, -110.56],
    [75.74, 486.27, -144.21],
    [60.86, 454.34, -141.72],
    [27.45, 459.94, -19.01],
    [27.18, 460.38, -32.10],
    [24.69, 460.47, -79.53],
    [26.29, 460.32, -55.84]
  ]
}
